pylibftdi/__init__.py
pylibftdi/__main__.py
pylibftdi/_base.py
pylibftdi/bitbang.py
pylibftdi/device.py
pylibftdi/driver.py
pylibftdi/examples/__init__.py
pylibftdi/examples/bit_server.py
pylibftdi/examples/info.py
pylibftdi/examples/lcd.py
pylibftdi/examples/led_flash.py
pylibftdi/examples/list_devices.py
pylibftdi/examples/magic_candle.py
pylibftdi/examples/midi_output.py
pylibftdi/examples/morse.py
pylibftdi/examples/pin_read.py
pylibftdi/examples/serial_loopback.py
pylibftdi/examples/serial_transfer.py
pylibftdi/serial_device.py
pylibftdi/util.py
pylibftdi-0.23.0.dist-info/LICENSE.txt
pylibftdi-0.23.0.dist-info/METADATA
pylibftdi-0.23.0.dist-info/WHEEL
pylibftdi-0.23.0.dist-info/RECORD
