Metadata-Version: 2.1
Name: pylibftdi
Version: 0.23.0
Summary: Pythonic interface to FTDI devices using libftdi.
Home-page: https://github.com/codedstructure/pylibftdi
License: MIT
Keywords: ftdi,libftdi,usb
Author: Ben Bass
Author-email: benbass@codedstructure.net
Requires-Python: >=3.7.0
Classifier: Development Status :: 4 - Beta
Classifier: Environment :: Console
Classifier: Intended Audience :: Developers
Classifier: License :: OSI Approved :: MIT License
Classifier: Operating System :: Microsoft :: Windows
Classifier: Operating System :: POSIX
Classifier: Programming Language :: Python
Classifier: Programming Language :: Python :: 3
Classifier: Programming Language :: Python :: 3.7
Classifier: Programming Language :: Python :: 3.8
Classifier: Programming Language :: Python :: 3.9
Classifier: Programming Language :: Python :: 3.10
Classifier: Programming Language :: Python :: 3.11
Classifier: Programming Language :: Python :: 3.12
Classifier: Programming Language :: Python :: 3.13
Classifier: Topic :: Scientific/Engineering
Classifier: Topic :: Software Development :: Embedded Systems
Classifier: Topic :: System :: Hardware
Project-URL: Documentation, https://pylibftdi.readthedocs.io/en/latest/
Project-URL: Repository, https://github.com/codedstructure/pylibftdi
